djangoup/__init__.py
djangoup/apps.py
djangoup/tests.py
djangoup/management/__init__.py
djangoup/management/commands/__init__.py
djangoup/management/commands/deploy.example.yml
djangoup/management/commands/deploy.py
djangoup/management/commands/gunicorn.conf.py
djangoup/management/commands/settings_init.example.py
django_up-0.2.1.dist-info/LICENSE
django_up-0.2.1.dist-info/METADATA
django_up-0.2.1.dist-info/WHEEL
django_up-0.2.1.dist-info/top_level.txt
django_up-0.2.1.dist-info/RECORD
